coldwavebook/__init__.py
coldwavebook-1.0.1.dist-info/LICENSE.txt
coldwavebook-1.0.1.dist-info/METADATA
coldwavebook-1.0.1.dist-info/WHEEL
coldwavebook-1.0.1.dist-info/top_level.txt
coldwavebook-1.0.1.dist-info/RECORD
